psychoevals/__init__.py
psychoevals/analysis.py
psychoevals/cognitive_state.py
psychoevals/eval.py
psychoevals/evaluation.py
psychoevals/moderation.py
psychoevals/qna_result.py
psychoevals/security.py
psychoevals/utils.py
psychoevals/agents/__init__.py
psychoevals/agents/base_eval_agent.py
psychoevals/agents/myers_briggs/__init__.py
psychoevals/agents/myers_briggs/mbti_statements.py
psychoevals/agents/myers_briggs/myers_briggs.py
psychoevals/agents/troll_agent/__init__.py
psychoevals/agents/troll_agent/troll_agent.py
tests/__init__.py
tests/test_mbti.py
tests/test_moderation.py
tests/test_security.py
tests/test_troll_agent.py
psychoevals-0.8.dist-info/METADATA
psychoevals-0.8.dist-info/WHEEL
psychoevals-0.8.dist-info/top_level.txt
psychoevals-0.8.dist-info/RECORD
