Metadata-Version: 2.1
Name: psychoevals
Version: 0.8
Author: John (@nextword)
Author-email: public@nextword.dev
Classifier: Development Status :: 3 - Alpha
Classifier: License :: OSI Approved :: MIT License
Classifier: Programming Language :: Python :: 3
Classifier: Programming Language :: Python :: 3.7
Requires-Python: >=3.7
Requires-Dist: openai (>=0.27.0)
Requires-Dist: pandas (>=1.3.0)
Requires-Dist: tenacity (>=8.0.0)
Requires-Dist: python-dotenv (>=0.15.0)
